atlaz/__init__.py
atlaz/utility.py
atlaz-10.0.1.dist-info/licenses/LICENSE
atlaz-10.0.1.dist-info/METADATA
atlaz-10.0.1.dist-info/WHEEL
atlaz-10.0.1.dist-info/top_level.txt
atlaz-10.0.1.dist-info/RECORD
